Metadata-Version: 2.1
Name: pressor
Version: 0.0.6
Summary: data press for python
Home-page: https://gitee.com/maxbanana
Author: hongbo liu
Author-email: 782027465@qq.com
License: Apache
Classifier: Programming Language :: Python :: 3
Classifier: License :: OSI Approved :: Apache Software License
Classifier: Operating System :: OS Independent
Requires-Python: >=3.6
License-File: LICENSE
Requires-Dist: bigtools>=0.1.2
Requires-Dist: jieba==0.42.1
Requires-Dist: requests>=2.31.0
Requires-Dist: lxml>=4.9.3
Requires-Dist: beautifulsoup4>=4.11.1
Requires-Dist: epubs>=0.0.3
Requires-Dist: ebooksp>=0.0.6
Requires-Dist: python-docx>=0.8.11
Requires-Dist: html2text
